Fleek/__init__.py
Fleek-0.0.0.1.dist-info/METADATA
Fleek-0.0.0.1.dist-info/WHEEL
Fleek-0.0.0.1.dist-info/top_level.txt
Fleek-0.0.0.1.dist-info/RECORD
